Experiment 4 - Subtractor/Full Subtractor/GM/fullsubtractor.v
module fullsubtractor(Difference, Borrow, A, B, Cin);
input A, B, Cin;
wire w1, w2, w3, w4, w5;
output Difference, Borrow;
xor x1(w1, A, B);
xor x2(Difference, w1, Cin);
not n1(w2, A);
and a1(w3, w2, B);
not n2(w4, w1);
and a2(w5, w4, Cin);
or o1(Borrow, w3, w5);
endmodule

Experiment 4 - Subtractor/Full Subtractor/DFM/testbencha1.v
module testbencha1;
reg A, B, Cin;
wire Difference, Borrow;
fullsubtractor uut(Difference, Borrow, A, B, Cin);
initial begin
$dumpfile("fullsubtractor.vcd");
$dumpvars();
A = 0;
B = 0;
Cin = 0;
#10
A = 0;
B = 0;
Cin = 1;
#10
A = 0;
B = 1;
Cin = 0;
#10
A = 0;
B = 1;
Cin = 1;
#10
A = 1;
B = 0;
Cin = 0;
#10
A = 1;
B = 0;
Cin = 1;
#10
A = 1;
B = 1;
Cin = 0;
#10
A = 1;
B = 1;
Cin = 1;
#10
$finish;
end
endmodule

Experiment 4 - Subtractor/Full Subtractor/GM/fullsubtractor.vcd
$date
	Tue Feb 18 21:13:14 2025
$end
$version
	Icarus Verilog
$end
$timescale
	1s
$end
$scope module testbencha1 $end
$var wire 1 ! Difference $end
$var wire 1 " Borrow $end
$var reg 1 # A $end
$var reg 1 $ B $end
$var reg 1 % Cin $end
$scope module uut $end
$var wire 1 # A $end
$var wire 1 $ B $end
$var wire 1 " Borrow $end
$var wire 1 % Cin $end
$var wire 1 ! Difference $end
$var wire 1 & w1 $end
$var wire 1 ' w2 $end
$var wire 1 ( w3 $end
$var wire 1 ) w4 $end
$var wire 1 * w5 $end
$upscope $end
$upscope $end
$enddefinitions $end
#0
$dumpvars
0*
1)
0(
1'
0&
0%
0$
0#
0"
0!
$end
#10
1"
1!
1*
1%
#20
0)
0*
1&
1(
0%
1$
#30
0!
1%
#40
0"
1!
0(
0'
0%
0$
1#
#50
0!
1%
#60
1)
0&
0%
1$
#70
1"
1!
1*
1%
