Experiment 3 - Adder/Full Adder/BM/fulladder.v
module fulladder(Sum, Carry, A, B, Cin);
input A, B, Cin;
output reg Sum, Carry;
always@(A, B, Cin)
begin
Sum = (A ^ B ^ Cin);
Carry = ((A&B)|(A&Cin)|(B&Cin));
end
endmodule

Experiment 3 - Adder/Full Adder/BM/testbencha1.v
module testbencha1;
reg A, B, Cin;
wire Sum, Carry;
fulladder uut(Sum, Carry, A, B, Cin);
initial begin
$dumpfile("fulladder.vcd");
$dumpvars();
A = 0;
B = 0;
Cin = 0;
#10
A = 0;
B = 0;
Cin = 1;
#10
A = 0;
B = 1;
Cin = 0;
#10
A = 0;
B = 1;
Cin = 1;
#10
A = 1;
B = 0;
Cin = 0;
#10
A = 1;
B = 0;
Cin = 1;
#10
A = 1;
B = 1;
Cin = 0;
#10
A = 1;
B = 1;
Cin = 1;
#10
$finish;
end
endmodule

Experiment 3 - Adder/Full Adder/BM/fulladder.vcd
$date
	Tue Feb 18 19:41:10 2025
$end
$version
	Icarus Verilog
$end
$timescale
	1s
$end
$scope module testbencha1 $end
$var wire 1 ! Sum $end
$var wire 1 " Carry $end
$var reg 1 # A $end
$var reg 1 $ B $end
$var reg 1 % Cin $end
$scope module uut $end
$var wire 1 # A $end
$var wire 1 $ B $end
$var wire 1 % Cin $end
$var reg 1 " Carry $end
$var reg 1 ! Sum $end
$upscope $end
$upscope $end
$enddefinitions $end
#0
$dumpvars
0%
0$
0#
0"
0!
$end
#10
1!
1%
#20
0%
1$
#30
1"
0!
1%
#40
0"
1!
0%
0$
1#
#50
1"
0!
1%
#60
0%
1$
#70
1!
1%
