Experiment 6 - Code Converters/Gray to Binary/Behavioral Modelling/gtob.v
module gtob(g3, g2, g1, g0, b3, b2, b1, b0);
input g3, g2, g1, g0;
output reg b3, b2, b1, b0;
always @(*) 
begin
b3 = g3;
b2 = b3 ^ g2;
b1 = b2 ^ g1;
b0 = b1 ^ g0;
end
endmodule

Experiment 6 - Code Converters/Gray to Binary/Dataflow Modelling/testgtob.v
module testgtob;
reg g0, g1, g2, g3;
wire b0, b1, b2, b3;
gtob uut(.g0(g0), .g1(g1), .g2(g2), .g3(g3), .b0(b0), .b1(b1), .b2(b2), .b3(b3));
initial begin
$dumpfile("gtob.vcd");
$dumpvars();
g3 = 0; g2 = 0; g1 = 0; g0 = 0; #10;
g3 = 0; g2 = 0; g1 = 0; g0 = 1; #10;
g3 = 0; g2 = 0; g1 = 1; g0 = 0; #10;
g3 = 0; g2 = 0; g1 = 1; g0 = 1; #10;
g3 = 0; g2 = 1; g1 = 0; g0 = 0; #10;
g3 = 0; g2 = 1; g1 = 0; g0 = 1; #10;
g3 = 0; g2 = 1; g1 = 1; g0 = 0; #10;
g3 = 0; g2 = 1; g1 = 1; g0 = 1; #10;
g3 = 1; g2 = 0; g1 = 0; g0 = 0; #10;
g3 = 1; g2 = 0; g1 = 0; g0 = 1; #10;
g3 = 1; g2 = 0; g1 = 1; g0 = 0; #10;
g3 = 1; g2 = 0; g1 = 1; g0 = 1; #10;
g3 = 1; g2 = 1; g1 = 0; g0 = 0; #10;
g3 = 1; g2 = 1; g1 = 0; g0 = 1; #10;
g3 = 1; g2 = 1; g1 = 1; g0 = 0; #10;
g3 = 1; g2 = 1; g1 = 1; g0 = 1; #10;
$finish;
end
endmodule

Experiment 6 - Code Converters/Gray to Binary/Behavioral Modelling/gtob.vcd
$date
	Thu Mar 27 17:49:55 2025
$end
$version
	Icarus Verilog
$end
$timescale
	1s
$end
$scope module testgtob $end
$var wire 1 ! b3 $end
$var wire 1 " b2 $end
$var wire 1 # b1 $end
$var wire 1 $ b0 $end
$var reg 1 % g0 $end
$var reg 1 & g1 $end
$var reg 1 ' g2 $end
$var reg 1 ( g3 $end
$scope module uut $end
$var wire 1 % g0 $end
$var wire 1 & g1 $end
$var wire 1 ' g2 $end
$var wire 1 ( g3 $end
$var reg 1 $ b0 $end
$var reg 1 # b1 $end
$var reg 1 " b2 $end
$var reg 1 ! b3 $end
$upscope $end
$upscope $end
$enddefinitions $end
$comment Show the parameter values. $end
$dumpall
$end
#0
$dumpvars
0(
0'
0&
0%
0$
0#
0"
0!
$end
#10
1$
1%
#20
1#
0%
1&
#30
0$
1%
#40
1$
1"
0%
0&
1'
#50
0$
1%
#60
0#
0%
1&
#70
1$
1%
#80
1#
1!
0%
0&
0'
1(
#90
0$
1%
#100
0#
0%
1&
#110
1$
1%
#120
0$
0"
0%
0&
1'
#130
1$
1%
#140
1#
0%
1&
#150
0$
1%
