Experiment 6 - Code Converters/Binary to Gray/Behavioral Modelling/btog.v
module btog (b1, b2, b3, b0, g1, g2, g3, g0);
input b1, b2, b3, b0;
output reg g1, g2, g3, g0;
always @(*) 
begin
g0 = b0 ^ b1;
g1 = b1 ^ b2;
g2 = b2 ^ b3;
g3 = b3;   
end
endmodule

Experiment 6 - Code Converters/Binary to Gray/Dataflow Modelling/testbtog.v
module testbtog;
reg b1, b2, b3, b0;
wire g1, g2, g3, g0;
btog uut(.b0(b0), .b1(b1), .b2(b2), .b3(b3), .g0(g0), .g1(g1), .g2(g2), .g3(g3));
initial begin
$dumpfile("btog.vcd");
$dumpvars();
b3=0; b2=0; b1=0; b0=0; #10;
b3=0; b2=0; b1=0; b0=1; #10;
b3=0; b2=0; b1=1; b0=0; #10;
b3=0; b2=0; b1=1; b0=1; #10;
b3=0; b2=1; b1=0; b0=0; #10;
b3=0; b2=1; b1=0; b0=1; #10;
b3=0; b2=1; b1=1; b0=0; #10;
b3=0; b2=1; b1=1; b0=1; #10;
b3=1; b2=0; b1=0; b0=0; #10;
b3=1; b2=0; b1=0; b0=1; #10;
b3=1; b2=0; b1=1; b0=0; #10;
b3=1; b2=0; b1=1; b0=1; #10;
b3=1; b2=1; b1=0; b0=0; #10;
b3=1; b2=1; b1=0; b0=1; #10;
b3=1; b2=1; b1=1; b0=0; #10;
b3=1; b2=1; b1=1; b0=1; #10;
$finish;
end
endmodule

Experiment 6 - Code Converters/Binary to Gray/Behavioral Modelling/btog.vcd
$date
	Thu Mar 27 17:31:16 2025
$end
$version
	Icarus Verilog
$end
$timescale
	1s
$end
$scope module testbtog $end
$var wire 1 ! g3 $end
$var wire 1 " g2 $end
$var wire 1 # g1 $end
$var wire 1 $ g0 $end
$var reg 1 % b0 $end
$var reg 1 & b1 $end
$var reg 1 ' b2 $end
$var reg 1 ( b3 $end
$scope module uut $end
$var wire 1 % b0 $end
$var wire 1 & b1 $end
$var wire 1 ' b2 $end
$var wire 1 ( b3 $end
$var reg 1 $ g0 $end
$var reg 1 # g1 $end
$var reg 1 " g2 $end
$var reg 1 ! g3 $end
$upscope $end
$upscope $end
$enddefinitions $end
$comment Show the parameter values. $end
$dumpall
$end
#0
$dumpvars
0(
0'
0&
0%
0$
0#
0"
0!
$end
#10
1$
1%
#20
1#
0%
1&
#30
0$
1%
#40
1"
0%
0&
1'
#50
1$
1%
#60
0#
0%
1&
#70
0$
1%
#80
1!
0%
0&
0'
1(
#90
1$
1%
#100
1#
0%
1&
#110
0$
1%
#120
0"
0%
0&
1'
#130
1$
1%
#140
0#
0%
1&
#150
0$
1%
