Experiment 4 - Subtractor/Full Subtractor/DFM/fullsubtractor.v
module fullsubtractor(Difference,Borrow, A, B, Cin);
input A, B, Cin;
output Difference,Borrow;
assign Difference = A ^ B ^ Cin;
assign Borrow = ((Cin&(~(A ^ B)))|((~A)&B));
endmodule

Experiment 4 - Subtractor/Full Subtractor/DFM/testbencha1.v
module testbencha1;
reg A, B, Cin;
wire Difference, Borrow;
fullsubtractor uut(Difference, Borrow, A, B, Cin);
initial begin
$dumpfile("fullsubtractor.vcd");
$dumpvars();
A = 0;
B = 0;
Cin = 0;
#10
A = 0;
B = 0;
Cin = 1;
#10
A = 0;
B = 1;
Cin = 0;
#10
A = 0;
B = 1;
Cin = 1;
#10
A = 1;
B = 0;
Cin = 0;
#10
A = 1;
B = 0;
Cin = 1;
#10
A = 1;
B = 1;
Cin = 0;
#10
A = 1;
B = 1;
Cin = 1;
#10
$finish;
end
endmodule

Experiment 4 - Subtractor/Full Subtractor/DFM/fullsubtractor.vcd
$date
	Tue Feb 18 21:15:21 2025
$end
$version
	Icarus Verilog
$end
$timescale
	1s
$end
$scope module testbencha1 $end
$var wire 1 ! Difference $end
$var wire 1 " Borrow $end
$var reg 1 # A $end
$var reg 1 $ B $end
$var reg 1 % Cin $end
$scope module uut $end
$var wire 1 # A $end
$var wire 1 $ B $end
$var wire 1 " Borrow $end
$var wire 1 % Cin $end
$var wire 1 ! Difference $end
$upscope $end
$upscope $end
$enddefinitions $end
#0
$dumpvars
0%
0$
0#
0"
0!
$end
#10
1"
1!
1%
#20
0%
1$
#30
0!
1%
#40
0"
1!
0%
0$
1#
#50
0!
1%
#60
0%
1$
#70
1"
1!
1%
