Experiment 3 - Adder/Full Adder/GM/fulladder.v
module fulladder(Sum, Carry, A, B, Cin);
input A, B, Cin;
wire w1, w2, w3;
output Sum, Carry;
xor x1(w1, A, B);
xor x2(Sum, w1, Cin);
and a1(w2, A, B);
and a2(w3, w1, Cin);
or o1(Carry, w2, w3);
endmodule

Experiment 3 - Adder/Full Adder/BM/testbencha1.v
module testbencha1;
reg A, B, Cin;
wire Sum, Carry;
fulladder uut(Sum, Carry, A, B, Cin);
initial begin
$dumpfile("fulladder.vcd");
$dumpvars();
A = 0;
B = 0;
Cin = 0;
#10
A = 0;
B = 0;
Cin = 1;
#10
A = 0;
B = 1;
Cin = 0;
#10
A = 0;
B = 1;
Cin = 1;
#10
A = 1;
B = 0;
Cin = 0;
#10
A = 1;
B = 0;
Cin = 1;
#10
A = 1;
B = 1;
Cin = 0;
#10
A = 1;
B = 1;
Cin = 1;
#10
$finish;
end
endmodule

Experiment 3 - Adder/Full Adder/GM/fulladder.vcd
$date
	Tue Feb 18 19:12:24 2025
$end
$version
	Icarus Verilog
$end
$timescale
	1s
$end
$scope module testbencha1 $end
$var wire 1 ! Sum $end
$var wire 1 " Carry $end
$var reg 1 # A $end
$var reg 1 $ B $end
$var reg 1 % Cin $end
$scope module uut $end
$var wire 1 # A $end
$var wire 1 $ B $end
$var wire 1 " Carry $end
$var wire 1 % Cin $end
$var wire 1 ! Sum $end
$var wire 1 & w1 $end
$var wire 1 ' w2 $end
$var wire 1 ( w3 $end
$upscope $end
$upscope $end
$enddefinitions $end
#0
$dumpvars
0(
0'
0&
0%
0$
0#
0"
0!
$end
#10
1!
1%
#20
1&
0%
1$
#30
1"
0!
1(
1%
#40
0"
1!
0(
0%
0$
1#
#50
1"
0!
1(
1%
#60
0(
0&
1'
0%
1$
#70
1!
1%
